odoo/addons/stock_move_propagate_first_move/README.rst
odoo/addons/stock_move_propagate_first_move/__init__.py
odoo/addons/stock_move_propagate_first_move/__manifest__.py
odoo/addons/stock_move_propagate_first_move/i18n/es.po
odoo/addons/stock_move_propagate_first_move/i18n/it.po
odoo/addons/stock_move_propagate_first_move/i18n/stock_move_propagate_first_move.pot
odoo/addons/stock_move_propagate_first_move/models/__init__.py
odoo/addons/stock_move_propagate_first_move/models/stock_move.py
odoo/addons/stock_move_propagate_first_move/models/stock_rule.py
odoo/addons/stock_move_propagate_first_move/readme/CONTRIBUTORS.rst
odoo/addons/stock_move_propagate_first_move/readme/DESCRIPTION.rst
odoo/addons/stock_move_propagate_first_move/static/description/icon.png
odoo/addons/stock_move_propagate_first_move/static/description/index.html
odoo/addons/stock_move_propagate_first_move/tests/__init__.py
odoo/addons/stock_move_propagate_first_move/tests/common.py
odoo/addons/stock_move_propagate_first_move/tests/test_stock_move_picking_type_origin_pull.py
odoo/addons/stock_move_propagate_first_move/tests/test_stock_move_picking_type_origin_pull_push.py
odoo/addons/stock_move_propagate_first_move/tests/test_stock_move_picking_type_origin_push.py
odoo/addons/stock_move_propagate_first_move/views/stock_move.xml
odoo_addon_stock_move_propagate_first_move-16.0.1.0.1.6.dist-info/METADATA
odoo_addon_stock_move_propagate_first_move-16.0.1.0.1.6.dist-info/WHEEL
odoo_addon_stock_move_propagate_first_move-16.0.1.0.1.6.dist-info/top_level.txt
odoo_addon_stock_move_propagate_first_move-16.0.1.0.1.6.dist-info/RECORD
